README.md
pyproject.toml
setup.py
example/__init__.py
example/train.py
example/visualize.py
mindsdb_forecast_visualizer/__about__.py
mindsdb_forecast_visualizer/__init__.py
mindsdb_forecast_visualizer.egg-info/PKG-INFO
mindsdb_forecast_visualizer.egg-info/SOURCES.txt
mindsdb_forecast_visualizer.egg-info/dependency_links.txt
mindsdb_forecast_visualizer.egg-info/requires.txt
mindsdb_forecast_visualizer.egg-info/top_level.txt
mindsdb_forecast_visualizer/config/__init__.py
mindsdb_forecast_visualizer/config/config.py
mindsdb_forecast_visualizer/core/__init__.py
mindsdb_forecast_visualizer/core/dispatcher.py
mindsdb_forecast_visualizer/core/forecaster.py
mindsdb_forecast_visualizer/core/plotter.py