Metadata-Version: 2.1
Name: mindsdb-forecast-visualizer
Version: 22.8.1.1
Summary: Companion package to visualizer forecasts made with MindsDB predictors.
Home-page: https://github.com/mindsdb/mindsdb_forecast_visualizer
Author: MindsDB Inc
Author-email: community@mindsdb.com
License: GPL-3.0
Download-URL: https://pypi.org/project/mindsdb_forecast_visualizer
Platform: UNKNOWN
Classifier: Programming Language :: Python :: 3
Classifier: License :: OSI Approved :: GNU General Public License v3 (GPLv3)
Classifier: Operating System :: OS Independent
Requires-Python: >=3.7
